Metadata-Version: 2.1
Name: altocumulus
Version: 2.3.0
Summary: Command line utilities for workflows on Terra or Cromwell
Author: Bo Li, Joshua Gould, Yiming Yang
Author-email: cumulus-support@googlegroups.com
License: BSD 3-Clause License
Project-URL: Repository, https://github.com/lilab-bcb/altocumulus
Project-URL: Documentation, https://altocumulus.readthedocs.io
Keywords: Terra,Cromwell
Classifier: License :: OSI Approved :: BSD License
Classifier: Intended Audience :: Developers
Classifier: Intended Audience :: Science/Research
Classifier: Natural Language :: English
Classifier: Operating System :: MacOS :: MacOS X
Classifier: Operating System :: Microsoft :: Windows
Classifier: Operating System :: POSIX :: Linux
Classifier: Programming Language :: Python :: 3
Classifier: Programming Language :: Python :: 3.8
Classifier: Programming Language :: Python :: 3.9
Classifier: Programming Language :: Python :: 3.10
Classifier: Topic :: Scientific/Engineering :: Bio-Informatics
Requires-Python: >=3.8
License-File: LICENSE
Requires-Dist: firecloud
Requires-Dist: fsspec
Requires-Dist: matplotlib
Requires-Dist: numpy
Requires-Dist: openpyxl
Requires-Dist: pandas
Requires-Dist: python-dateutil
Requires-Dist: six
Requires-Dist: stratocumulus (>=0.2.0)
Provides-Extra: test
Requires-Dist: pytest ; extra == 'test'
